clover/__init__.py
clover/align.py
clover/load_config.py
clover/main.py
clover/tree.py
tests/__init__.py
tests/test_align.py
tests/test_clust.py
tests/test_tree.py
dna_clover-1.2.dist-info/LICENSE
dna_clover-1.2.dist-info/METADATA
dna_clover-1.2.dist-info/WHEEL
dna_clover-1.2.dist-info/entry_points.txt
dna_clover-1.2.dist-info/top_level.txt
dna_clover-1.2.dist-info/RECORD
