Metadata-Version: 2.1
Name: dna-clover
Version: 1.2
Summary: Tree structure-based efficient DNA clustering for DNA-based data storage
Home-page: http://github.com/storborg/funniest
Author: Guanjin qu
Author-email: guanjinqu@tju.edu.cn
License: GNU
License-File: LICENSE
